Workbook

Sheet Dépenses
A1: Fournisseur | B1: Facture | C1: Date | D1: Montant | J1: Fournisseur
A2: SMPA | B2: F0590 | C2: 45022 | D2: 500.5 | J2: SMPA
A3: SMPA | B3: F0824 | C3: 45087 | D3: 812.4 | J3: SNAPRINT
A4: SMPA | B4: F0951 | C4: 45119 | D4: 799.385 | J4: Maison D'Art
A5: SMPA | B5: F1100 | C5: 45141 | D5: 666.112 | J5: Kamel hidri
A6: SMPA | B6: F1248 | C6: 45193 | D6: 616 | J6: TOUT BUREAU
A7: SMPA | B7: F1320 | C7: 45210 | D7: 663.444 | J7: NATBAG
A8: SNAPRINT | B8: 2023-0195 | C8: 45251 | D8: 1081.75 | J8: ORIENTAL DESIGN
A9: SMPA | B9: F1496 | C9: 45251 | D9: 462.216 | J9: Fehri Bel hadj
A10: Maison D'Art | B10: 292 | C10: 45266 | D10: 934.58 | J10: KACO SA
A11: Kamel hidri | B11: - | C11: 45266 | D11: 420.551 | J11: ASCOM
A12: TOUT BUREAU | B12: F2313884 | C12: 45275 | D12: 762 | J12: My Print Tunisia
A13: NATBAG | B13: 000059 | C13: 45278 | D13: 1690.2 | J13: Helmi Abbassi
A14: ORIENTAL DESIGN | B14: 20230162V | C14: 45281 | D14: 1900 | J14: Ben Ghorbal Kawther
A15: Fehri Bel hadj | B15: 022/2023 | C15: 45281 | D15: 1425 | J15: Cabinet Fethi Hamrouni
A16: SNAPRINT | B16: 2023-01955 | C16: 45281 | D16: 3640 | J16: Orange Tunisie
A17: KACO SA | B17: 202308 | C17: 45285 | D17: 1800 | J17: Foire International Sousse
A18: SMPA | B18: F1558 | C18: 45288 | D18: 504.462 | J18: ALCHIMY
A19: ASCOM | B19: FC256 | C19: 45315 | D19: 950 | J19: BIO SPACE
A20: Kamel hidri | B20: - | C20: 45307 | D20: 3932.2499 | J20: 3P
A21: Maison D'Art | B21: 301 | C21: 45307 | D21: 8411.2149 | J21: SBCD
A22: My Print Tunisia | B22: 24044 | C22: 45484 | D22: 1797 | J22: LEM
A23: Helmi Abbassi | B23: 393 | C23: 45490 | D23: 375.2 | J23: KOBOX
A24: Ben Ghorbal Kawther | B24: 3732 | C24: 45488 | D24: 210.25 | J24: Karim Balah
A25: Cabinet Fethi Hamrouni | B25: ac073/24 | C25: 45493 | D25: 1500.476 | J25: Yosra Sayah
A26: Orange Tunisie | B26: 2401316943 | C26: 45292 | D26: 64.286 | J26: Recharge carte tech
A27: Orange Tunisie | B27: 2401316943 | C27: 45323 | D27: 64.286 | J27: Majdi PHOTOGRAPHE
A28: Orange Tunisie | B28: 2401316943 | C28: 45352 | D28: 64.286 | J28: Sofien Cherif
A29: Orange Tunisie | B29: 2401316943 | C29: 45383 | D29: 64.286 | J29: CNSS
A30: Orange Tunisie | B30: 2401316943 | C30: 45413 | D30: 64.286 | J30: Pénalité
A31: Orange Tunisie | B31: 2401316943 | C31: 45444 | D31: 64.286 | J31: Lazhar Riahi
A32: Orange Tunisie | B32: 2401316943 | C32: 45474 | D32: 64.286 | J32: Riadh Laouiti
A33: Orange Tunisie | B33: 2401316943 | C33: 45505 | D33: 64.286 | J33: Zitoun Artisanat
A34: Foire International Sousse | B34: FA2400470 | C34: 45501 | D34: 365 | J34: EL FEKI BILEL
A35: ALCHIMY | B35: FAC023 | C35: 45462 | D35: 1116.9 | J35: Chedly Gara
A36: BIO SPACE | C36: 45439 | D36: 600 | J36: Outils emballage
A37: Fehri Bel hadj | C37: 45352 | D37: 21028.03 | J37: Open Space Lab
A38: Orange Tunisie | B38: 2401316943 | C38: 45536 | D38: 64.286 | J38: Gaya
A39: Orange Tunisie | B39: 2401316943 | C39: 45566 | D39: 64.286 | J39: Jeux bittounsi
A40: 3P | B40: FAC241984 | C40: 45617 | D40: 625 | J40: Zoub ceramic
A41: SBCD | B41: FA244908 | C41: 45617 | D41: 65.4 | J41: Yassin Calligraphie
A42: LEM | B42: FAC52 | C42: 45604 | D42: 1250 | J42: Cartons Fouchana
A43: SBCD | B43: FA244776 | C43: 45610 | D43: 9000 | J43: Transport Fehri
A44: KOBOX | B44: FAC-242412 | C44: 45635 | D44: 207.5 | J44: Mondher cuivre
A45: KOBOX | B45: FAC-242381 | C45: 45631 | D45: 1335 | J45: Huissier Notaire
A46: Karim Balah | C46: 45631 | D46: 16095 | J46: moez cire
A47: Yosra Sayah | C47: 45663 | D47: 1800 | J47: Dorry Bio
A48: Recharge carte tech | C48: 45632 | D48: 440 | J48: l'mprimheure
A49: Majdi PHOTOGRAPHE | C49: 45632 | D49: 230 | J49: Karima Dachraoui
A50: Sofien Cherif | C50: 45651 | D50: 420 | J50: Hide Away Tunisia
A51: CNSS | C51: 45657 | D51: 550 | J51: Brothers Phone Store
A52: Pénalité | C52: 45352 | D52: 250 | J52: Librairie Attakwa
A53: Lazhar Riahi | C53: 45359 | D53: 900 | J53: MIM Fitness Megrine
A54: Sté Laouiti Artisanat | C54: 45651 | D54: 818 | J54: Quincaillerie Zormani
A55: ORIENTAL DESIGN | C55: 45663 | D55: 830 | J55: Laouiti Artisanat
A56: CNSS | C56: 45648 | D56: 90 | J56: Société Moderne de Cuivre
A57: Helmi Abbassi | C57: 45657 | D57: 90 | J57: 2M STONEWARE
... A67: Zoub ceramic | C67: 45657 | D67: 300 | J67: KAMTRADE
A68: NATBAG | B68: FCT-NAT000012 | C68: 45657 | D68: 2626 | J68: Vivo Energy (Shell)
A69: Yassin Calligraphie | C69: 45377 | D69: 350 | J69: Tunisie Telecom
A70: Karim Balah | C70: 45413 | D70: 500 | J70: ZOUBA THE CERAMIC STUDIO
A71: 3P | C71: 45383 | D71: 656.6 | J71: Delta Distribution
A72: KACO SA | C72: 45413 | D72: 330 | J72: Elementor Ltd.
A73: 3P | C73: 45474 | D73: 480 | J73: Batinconfort Mestiri
A74: Cartons Fouchana | C74: 45453 | D74: 380 | J74: LA QUINCAILLERIE DU SAHEL
A75: Transport Fehri | C75: 45352 | D75: 120 | J75: Quincaillerie Générale
A76: Mondher cuivre | C76: 45323 | D76: 140 | J76: Sté Laouiti Artisanat
A77: Huissier Notaire | C77: 45352 | D77: 70 | J77: OCEAN BOUGIES
A78: moez cire | C78: 45376 | D78: 75 | J78: Bannour Ahmed
A79: Dorry Bio | C79: 45352 | D79: 75 | J79: Bilel Feki
A80: SBCD | C80: 45383 | D80: 189 | J80: Aramex
A81: l'mprimheure | C81: 45649 | D81: 100 | J81: SBCD
A82: Karima Dachraoui | B82: 005/2025 | D82: 510 | J82: OXA HOST SARL
A83: EL FEKI BILEL | C83: 45366 | D83: 894 | J83: PROSCOM
A84: Hide Away Tunisia | B84: 8485 | C84: 45659 | D84: 1000 | J84: PRINTWORKS
A85: Brothers Phone Store | B85: 2 | C85: 45678 | D85: 2350 | J85: Soumaya Sellaouti
A86: Librairie Attakwa | C86: 45685 | D86: 35.294
A87: MIM Fitness Megrine | B87: 109 | C87: 45680 | D87: 1250
A88: Quincaillerie Zormani | B88: 2025/000004 | C88: 45663 | D88: 386.56
A89: Sté Laouiti Artisanat | C89: 45681 | D89: 2860.5
A90: Société Moderne de Cuivre | B90: FA06572 | C90: 45684 | D90: 37
A91: 2M STONEWARE | B91: 177 | C91: 45705 | D91: 1948
A92: 3P PRINT-PRODUCTION-FIXELS | B92: FAC250375 | C92: 45712 | D92: 50
A93: ENNAIM Céramique | B93: 6468 | C93: 45707 | D93: 2900
A94: Dar El Marsa | B94: 34472 | C94: 45709 | D94: 205.607
A95: Fabripierre | B95: 20250007 | C95: 45709 | D95: 332.8
A96: HELMI ABASSI | B96: 141 | C96: 45699 | D96: 14
A97: HELMI ABASSI | B97: 214 | C97: 45715 | D97: 130
A98: MHN lustres en nattes | B98: FAC/2025/00030 | C98: 45693 | D98: 1836.2
A99: ORIENTAL DESIGN | B99: 20250026V | C99: 45714 | D99: 13050
A100: Parashop | B100: INV-2022-0029748 | C100: 45691 | D100: 164.4
A101: Vivo Energy (Shell) | B101: 32158669 | C101: 45716 | D101: 305.883
A102: Fabripierre | B102: 20250006 | C102: 45693 | D102: 1634.465
A103: TRANSAF | B103: (non précisé) | C103: 45698 | D103: 52
A104: ORIENTAL DESIGN | B104: 20250019V | C104: 45700 | D104: 426
A105: ALCHIMY | B105: 5 | C105: 45700 | D105: 96
A106: Karima Dachraoui | B106: 009/2025 | C106: 45701 | D106: 255
A107: L'avenir | C107: 45706 | D107: 92
A108: KAMTRADE | B108: FAC-2500410 | C108: 45716 | D108: 1630
A109: KAMTRADE | B109: FAC-2500485 | C109: 45729 | D109: 1150.45
...

Sheet Revenus par client
A1: Client | B1: Total en DT | C1: Nombre de marchés | D1: % CA
A2: SMPA | B2: =SUMIF(Dépenses!A:A,'Revenus par client'!A2,Dépenses!D:D) -> 5024.519 | C2: =COUNTIF(Dépenses!A:A,'Revenus par client'!A2) -> 8 | D2: =B2/$B$86 -> 0.026887915
A3: SNAPRINT | B3: =SUMIF(Dépenses!A:A,'Revenus par client'!A3,Dépenses!D:D) -> 4721.75 | C3: =COUNTIF(Dépenses!A:A,'Revenus par client'!A3) -> 2 | D3: =B3/$B$86 -> 0.025267694
A4: Maison D'Art | B4: =SUMIF(Dépenses!A:A,'Revenus par client'!A4,Dépenses!D:D) -> 9345.7949 | C4: =COUNTIF(Dépenses!A:A,'Revenus par client'!A4) -> 2 | D4: =B4/$B$86 -> 0.050012536
A5: Kamel HYDRY | B5: =SUMIF(Dépenses!A:A,'Revenus par client'!A5,Dépenses!D:D) -> 0 | C5: =COUNTIF(Dépenses!A:A,'Revenus par client'!A5) -> 0 | D5: =B5/$B$86 -> 0
A6: TOUT BUREAU | B6: =SUMIF(Dépenses!A:A,'Revenus par client'!A6,Dépenses!D:D) -> 762 | C6: =COUNTIF(Dépenses!A:A,'Revenus par client'!A6) -> 1 | D6: =B6/$B$86 -> 0.0040777219
A7: NATBAG | B7: =SUMIF(Dépenses!A:A,'Revenus par client'!A7,Dépenses!D:D) -> 4316.2 | C7: =COUNTIF(Dépenses!A:A,'Revenus par client'!A7) -> 2 | D7: =B7/$B$86 -> 0.023097458
A8: ORIENTAL DESIGN | B8: =SUMIF(Dépenses!A:A,'Revenus par client'!A8,Dépenses!D:D) -> 40138 | C8: =COUNTIF(Dépenses!A:A,'Revenus par client'!A8) -> 13 | D8: =B8/$B$86 -> 0.21479213
A9: Fehri Bel hadj | B9: =SUMIF(Dépenses!A:A,'Revenus par client'!A9,Dépenses!D:D) -> 22453.03 | C9: =COUNTIF(Dépenses!A:A,'Revenus par client'!A9) -> 2 | D9: =B9/$B$86 -> 0.12015382
A10: KACO SA | B10: =SUMIF(Dépenses!A:A,'Revenus par client'!A10,Dépenses!D:D) -> 2130 | C10: =COUNTIF(Dépenses!A:A,'Revenus par client'!A10) -> 2 | D10: =B10/$B$86 -> 0.011398356
A11: ASCOM | B11: =SUMIF(Dépenses!A:A,'Revenus par client'!A11,Dépenses!D:D) -> 950 | C11: =COUNTIF(Dépenses!A:A,'Revenus par client'!A11) -> 1 | D11: =B11/$B$86 -> 0.005083774
A12: My Print Tunisia | B12: =SUMIF(Dépenses!A:A,'Revenus par client'!A12,Dépenses!D:D) -> 1797 | C12: =COUNTIF(Dépenses!A:A,'Revenus par client'!A12) -> 1 | D12: =B12/$B$86 -> 0.0096163598
A13: Helmi Abbassi | B13: =SUMIF(Dépenses!A:A,'Revenus par client'!A13,Dépenses!D:D) -> 465.2 | C13: =COUNTIF(Dépenses!A:A,'Revenus par client'!A13) -> 2 | D13: =B13/$B$86 -> 0.0024894438
... A82: Soumaya Sellaouti | B82: =SUMIF(Dépenses!A:A,'Revenus par client'!A82,Dépenses!D:D) -> 2048 | C82: =COUNTIF(Dépenses!A:A,'Revenus par client'!A82) -> 2 | D82: =B82/$B$86 -> 0.010959546
A86: Total | B86: =SUM(B2:B82) -> 186869.05

Sheet Bilan
A3: Étiquettes de lignes | B3: Somme de Total en DT | C3: Somme de Nombre de marchés | D3: Somme de % CA
A4: 2.11 STONEWARE | B4: 1948 | C4: 1 | D4: 0.0088409465
A5: 3P | B5: 1761.6 | C5: 3 | D5: 0.007994975
A6: 3P PRINT-PRODUCTION-FIXELS | B6: 150 | C6: 2 | D6: 0.00068077104
A7: ALCHIMY | B7: 1212.9 | C7: 2 | D7: 0.0055047146
A8: Aramex | B8: 334 | C8: 12 | D8: 0.0015158502
A9: ASCOM | B9: 950 | C9: 1 | D9: 0.0043115499
A10: Bannour Ahmed | B10: 650 | C10: 2 | D10: 0.0029500078
A11: Batinconfort Mestiri | B11: 29.649 | C11: 1 | D11: 0.0001345612
A12: Ben Ghorbal Kawther | B12: 294.35 | C12: 2 | D12: 0.0013358997
A13: BIO SPACE | B13: 600 | C13: 1 | D13: 0.0027230841
A14: Brothers Phone Store | B14: 2350 | C14: 1 | D14: 0.010665413
A15: Cabinet Fethi Hamrouni | B15: 1500.476 | C15: 1 | D15: 0.0068098707
... A86: Total général | B86: 220338.4 | C86: 185 | D86: 1

Sheet Feuille4
A1: Client | B1: Total en DT | C1: Nombre de marchés | D1: % CA
A2: 3P | B2: 1761.6 | C2: 3 | D2: 0.007994975

Sheet Feuille5
A1: Client | B1: Total en DT | C1: Nombre de marchés | D1: % CA
A2: Cabinet Fethi Hamrouni | B2: 1500.476 | C2: 1 | D2: 0.0068098707

Sheet Feuille6
A1: Client | B1: Total en DT | C1: Nombre de marchés | D1: % CA
A2: 3P PRINT-PRODUCTION-FIXELS | B2: 150 | C2: 2 | D2: 0.00068077104

Sheet Feuille7
A1: Client | B1: Total en DT | C1: Nombre de marchés | D1: % CA
A2: ALCHIMY | B2: 1212.9 | C2: 2 | D2: 0.0055047146
