Workbook

Sheet Settings
A1: Settings
A3: Company Details
A5: Company Name | B5: SOUGUI ESHOP | E5: Enable
A6: Company Slogan (Optional) | B6: My company slogan | E6: Disable
A8: Company Address
A10: Building/House Number | B10: 18
A11: Street | B11: Rue Mokhtar Attia
A12: Town/City | B12: Megrine
A13: County/Province
A14: State/Province | B14: Ben Arous
A15: ZIP/Postal Code | B15: 2033
A17: Tel. | B17: +216 55 466 087
A18: Fax
A19: E-mail | B19: contact@sougui.tn
A20: Website | B20: www.sougui.tn
A22: Person/Department to contact
A23: Contact Tel. Number
A25: Country Specific Settings
A27: Select Relevant | B27: Sales Tax
A30: Color Scheme
A32: Design Picker | B32: Blue

Sheet Facture
B1: =IF(Settings!$E$5="Enable",Settings!$B$5,"") -> SOUGUI ESHOP | K1: Facture
B2: =IF(Settings!$E$6="Enable",Settings!$B$6,"")
H4: Date: | J4: =TODAY() -> 46081
H5: Facture #: | J5: FAC25-32
H6: Client ID | J6: -
B9: Expéditeur : | H9: A envoyer à :
B10: Nom | C10: SOUGUI E SHOP | H10: Nom | I10: Bank ABC Tunis
B11: MF | C11: 1797689/E | H11: Matricule Fiscal | I11: =VLOOKUP($I$10,Adresses!A2:C10482,4,0) -> #REF!
B12: Adresse | C12: 18 Rue Mokhtar Attia Megrine,Ben Arous 2033 | H12: Adresse | I12: =VLOOKUP($I$10,Adresses!A2:C1048576,2,0) -> Rue du Lac d'Annecy , Tunis 1053
B13: Téléphone | C13: +216 55 466 087 | H13: Téléphone
B16: Référence | C16: Description | H16: PU HT | I16: Quantité | J16: Prix Total HT | Q16: Mode de paiement: 50% à l'avance , 50% à la livraison
B17: SM-001 | C17: Saphir Majesté | H17: 220 | I17: 5 | J17: =H17*I17 -> 1100
B18: AI-001 | C18: Azur Impérial | H18: 170 | I18: 15 | J18: 2550
B19: IMP-001 | C19: Impérial d'or | H19: 170 | I19: 20 | J19: 3400
B20: Pers | C20: Packaging & personnalisation | H20: 425 | I20: 1 | J20: 425
B34: Conditions de paiement : | I34: Montant Total HT | J34: =SUM($J$17:$K$32) -> 7475
B35: Les modes de paiement acceptés incluent le chèque et le virement bancaire | I35: TVA | J35: 0
I36: Timbre | J36: 1 | K36: 1
B37: Détails bancaires | I37: Avance 50% HT | J37: =J34*0.5 -> 3737.5
B38: RIB | C38: 04058144008283136345 | I38: Total Avance TTC | J38: =(J37*1)+J36 -> 3738.5
B39: IBAN TN5904058144008283136345
B40: Domiciliation : Attijari Bank Tunis
B42: Arrêté la présente FACTURE à la somme de trois mille sept cent trente huit dinars cinq cent millimes tunisiens
F45: Thank you for your business!
B46: =Settings!$B$10&" "&Settings!$B$11&", "&Settings!$B$12&IF(ISBLANK(Settings!$B$13),", ",", "&Settings!$B$13&", ")&IF(ISBLANK(Settings!$B$14),"",""&Settings!$B$14&", ")&Settings!$B$15 -> 18 Rue Mokhtar Attia , Megrine, Ben Arous, 2033
B47: ="Tel: "&Settings!$B$17&" Fax: "&Settings!$B$18&IF(ISBLANK(Settings!$B$19)," "," E-mail: "&Settings!$B$19)&IF(ISBLANK(Settings!$B$20)," "," Web: "&Settings!$B$20) -> Tel: +216 55 466 087 Fax: E-mail: contact@sougui.tn Web: www.sougui.tn

Sheet Devis
C1: =IF(Settings!$E$5="Enable",Settings!$B$5,"") -> SOUGUI ESHOP | J1: DEVIS
B2: =IF(Settings!$E$6="Enable",Settings!$B$6,"")
H4: Date: | J4: =TODAY() -> 46081
H5: Devis #: | J5: DEV25-12
H6: Client ID | J6: -
B9: Expéditeur : | H9: A envoyer à :
B10: Nom | C10: SOUGUI E SHOP | H10: Nom | I10: Lilas
B11: MF | C11: 1797689/E | H11: Matricule Fiscal | I11: =VLOOKUP($I$10,Adresses!A2:C10482,4,0) -> #REF!
B12: Adresse | C12: 18 Rue Mokhtar Attia Megrine,Ben Arous 2033 | H12: Adresse | I12: =VLOOKUP($I$10,Adresses!A2:C1048576,2,0) -> 5 Rue de l'énergie éolienne ZI Charguia 1 , Tunis Carthage 2035
B13: Téléphone | C13: +216 55 466 087 | H13: Téléphone | I13: =VLOOKUP($I$10,Adresses!A2:B10482,3,0) -> #REF!
B16: Référence | C16: Description | H16: PU HT | I16: Quantité | J16: Prix Total HT
B17: SB-01 | C17: Stylo Blanc 1 | H17: 1.15 | I17: 1500 | J17: =IF(B17="","",H17*I17) -> 1725
B18: Pers | C18: Personnalisation | H18: 0.35 | I18: 1500 | J18: =IF(B18="","",H18*I18) -> 525
J19: =IF(B19="","",H19*I19)
B34: Conditions de paiement : | I34: Montant Total HT | J34: =SUM($J$17:$K$32) -> 2250
B35: Les modes de paiement acceptés incluent le chèque et le virement bancaire
I37: Timbre | J37: 1 | K37: 1
B38: Détails bancaires | I38: TVA | J38: 0.19
B39: Banque | C39: Agence | D39: Compte | E39: Clé | I39: Total TTC | J39: =(J34*1.19)+J37 -> 2678.5
B40: =" 00004" -> 00004 | C40: ="00144" -> 00144 | D40: 1440082831363 3
C41: Domiciliation : Attijari Bank Tunis | P41: Mode de paiement : 30% à l'avance 70% à la livraison
C42: IBAN TN5904058144008283136345
B43: Arrêté le présent DEVIS à la somme de deux mille six cent soixante huit dinars cinq cent millimes tunisiens | O43: Mode de paiement : 30% à l'avance 70% à la livraison
B44: Thank you for your business!
B45: ="Si vous avez des questions concernant ce Devis, veuillez nous contacter."&Settings!$B$23 -> Si vous avez des questions concernant ce Devis, veuillez nous contacter.
B47: ="Tel: "&Settings!$B$17&" Fax: "&Settings!$B$18&IF(ISBLANK(Settings!$B$19)," "," E-mail: "&Settings!$B$19)&IF(ISBLANK(Settings!$B$20)," "," Web: "&Settings!$B$20) -> Tel: +216 55 466 087 Fax: E-mail: contact@sougui.tn Web: www.sougui.tn
B48: =Settings!$B$10&" "&Settings!$B$11&", "&Settings!$B$12&IF(ISBLANK(Settings!$B$13),", ",", "&Settings!$B$13&", ")&IF(ISBLANK(Settings!$B$14),"",""&Settings!$B$14&", ")&Settings!$B$15 -> 18 Rue Mokhtar Attia , Megrine, Ben Arous, 2033

Sheet Adresses
A1: Nom Client | B1: Adresse | C1: MF
A2: Attijari Bank | B2: 24 Av Hedi Karray, Tunis 1080 | C2: 000121J/P/M000
A3: Attijari Leasing | B3: Rue Lac d'Annecy , les Berges du Lac, 1059, Tunis | C3: 496311P/A/M/000
A4: SAMFI | B4: Route de sousse km14, Hamman-Lif, Tunisia | C4: 1070417 T/A/M/000
A5: WIFAK INTERNATIONAL BANK | B5: Zone D'activités Kheireddine, Les Berges du Lac III 2015 Kram | C5: 0798651L/P/M/000
A6: Force Management Training | B6: 63 Rue Ibn Rachiq Avenue Mohamed 5 | C6: 1566008H
A7: Tunis Call Center | B7: 2 Rue d'Argentine , Tunis Belvédère , Tunis 1002 Tunisie | C7: 0633781K/A/M/000
A8: Focus Tunisie | B8: Z.I Chotrana II, Ariana 2036, Ariana, Tunisia
A9: Everience | B9: 21 rue Jérusalem، SANA Business Center, Tunis 1002 | C9: 1144512Z
A10: SOTIC | B10: 152 Avenue 2 Mars GP1 KH 14 , Hammam Lif 2050 | C10: 46020C/A/M
A11: SIRYOS | B11: Rue Safia Chamia, Immobilière Khairi, 5ème étage Centre Urbain nord
A12: Lilas | B12: 5 Rue de l'énergie éolienne ZI Charguia 1 , Tunis Carthage 2035 | C12: 492586 Z/A/M/000
A13: Bank ABC Tunis | B13: Rue du Lac d'Annecy , Tunis 1053 | C13: 0048074BNM00

Sheet Historiques Factures Achat
A1: Numéro Facture | B1: Description | C1: Fournisseurs | D1: Montant HT | E1: Date | J1: Numéro Chéque | K1: Description | L1: Fournisseurs | M1: Montant TTC | N1: Date
A2: 24044 | B2: Achat 100 coffrets diffiseurs | C2: myprint | D2: 1797 | E2: 45484 | J2: 30 | K2: Avance Emballage | L2: MyPrint | M2: 1000
A3: 393 | B3: Achat Rollup+flyers | C3: Helmi abassi | D3: 375.2 | E3: 45490 | J3: 31 | K3: Parfum Moez | L3: Moez | M3: 1276
A4: 3732 | B4: Achat 250 Sacs | C4: Ben Ghorbel Kawther | D4: 210.25 | E4: 45488 | J4: 32 | K4: Montant restant Emballage | L4: MyPrint | M4: 1139.206
A5: ac073/24 | B5: Honoraires commissaire | C5: Fethi Hamrouni | D5: 1500 | E5: 45493 | J5: 33 | K5: Flyers et rollup | L5: Helmi | M5: 447.448
B6: Foire Sousse | C6: Sousse | D6: 430 | J6: 34 | K6: Avance Fethi commissaire | L6: Fethi hamrouni | M6: 900
J7: 35 | K7: Sofien + RNE | L7: Sofiene Cherif | M7: 130

Sheet Historiques Factures Vente
A1: Numéro Facture | B1: Description | C1: Client | D1: Montant HT | E1: Date
A2: FAC24-010 | B2: 2 Coffrets à Thé | C2: Attijari Bank | D2: 490 | E2: 45412
A3: FAC24-011 | B3: Facture Hanine SAMFI | C3: SAMFI | D3: 631 | E3: 45414
A4: FAC24-012 | B4: QR CODE EN BOIS | C4: WIFAK INTERNATIONAL BANK | D4: 845 | E4: 45427
A5: FAC24-013 | B5: Facture Hanine SAMFI | C5: SAMFI | D5: 727 | E5: 45440
A6: FAC24-014 | B6: Facture Ness bekri 9alou | C6: Force Management | D6: 31 | E6: 45455
A7: FAC24-015 | B7: Facture 600 porte clés | C7: WIFAK INTERNATIONAL BANK | D7: 4150 | E7: 45467
A8: FAC24-016 | B8: Facture Hanine SAMFI | C8: SAMFI | D8: 544 | E8: 45474
A9: FAC24-017 | B9: Facture Hanine SAMFI | C9: SAMFI | D9: 744 | E9: 45503
A10: FAC24-018 | B10: Facture Hanine SAMFI | C10: SAMFI | D10: 544 | E10: 45541
