Workbook

Sheet Dashboard
A3: Total Ventes (DT) | B3: =SUM(Sheet1!F2:F1000) -> 26859
A4: Total Remises (DT) | B4: =SUM(Sheet1!G2:G1000) -> 2321
A5: Nombre de Tickets | B5: =COUNTA(Sheet1!B2:B1000) -> 516
A8: Répartition par Type de Paiement | D8: Total par Jour
A9: Type | B9: Total (DT) | D9: Date | E9: Total (DT)
A10: Espèces | B10: =SUMIF(Sheet1!H2:H1000,"Espèces",Sheet1!F2:F1000) -> 15726
A11: Carte | B11: =SUMIF(Sheet1!H2:H1000,"Carte",Sheet1!F2:F1000) -> 11133 | D11: 45882 | E11: =SUMIF(Sheet1!$A$2:$A$1000,D11,Sheet1!$F$2:$F$1000) -> 975
D12: 45883 | E12: =SUMIF(Sheet1!$A$2:$A$1000,D12,Sheet1!$F$2:$F$1000) -> 864
D13: 45884 | E13: =SUMIF(Sheet1!$A$2:$A$1000,D13,Sheet1!$F$2:$F$1000) -> 565
D14: 45885 | E14: =SUMIF(Sheet1!$A$2:$A$1000,D14,Sheet1!$F$2:$F$1000) -> 1910
D15: 45886 | E15: =SUMIF(Sheet1!$A$2:$A$1000,D15,Sheet1!$F$2:$F$1000) -> 275
D16: 45887 | E16: =SUMIF(Sheet1!$A$2:$A$1000,D16,Sheet1!$F$2:$F$1000) -> 565
D17: 45888 | E17: =SUMIF(Sheet1!$A$2:$A$1000,D17,Sheet1!$F$2:$F$1000) -> 505
D18: 45889 | E18: =SUMIF(Sheet1!$A$2:$A$1000,D18,Sheet1!$F$2:$F$1000) -> 535
D19: 45890 | E19: =SUMIF(Sheet1!$A$2:$A$1000,D19,Sheet1!$F$2:$F$1000) -> 805
D20: 45891 | E20: =SUMIF(Sheet1!$A$2:$A$1000,D20,Sheet1!$F$2:$F$1000) -> 435
D21: 45892 | E21: =SUMIF(Sheet1!$A$2:$A$1000,D21,Sheet1!$F$2:$F$1000) -> 290
D22: 45893 | E22: =SUMIF(Sheet1!$A$2:$A$1000,D22,Sheet1!$F$2:$F$1000) -> 563
D23: 45894 | E23: =SUMIF(Sheet1!$A$2:$A$1000,D23,Sheet1!$F$2:$F$1000) -> 390
... D62: 45933 | E62: =SUMIF(Sheet1!$A$2:$A$1000,D62,Sheet1!$F$2:$F$1000) -> 827

Sheet Sheet1
A1: Date | B1: Produit | C1: Quantité | D1: Prix Unitaire (DT) | E1: Remise (%) | F1: Montant Total (DT) | G1: Montant Remise (DT) | H1: Type de Paiement (Espèces / Carte) | I1: Client (optionnel) | J1: Remarques
A2: 45911 | B2: Plateau 30*10 | C2: 1 | D2: 70 | F2: =C2*D2*(1-E2/100) -> 70 | G2: =C2*D2*(E2/100) -> 0 | H2: Espèces
A3: 45911 | B3: Plateau 30*10 | C3: 1 | D3: 70 | F3: =C3*D3*(1-E3/100) -> 70 | G3: =C3*D3*(E3/100) -> 0 | H3: carte
A4: 45911 | B4: Plateau 20*10 | C4: 1 | D4: 55 | F4: =C4*D4*(1-E4/100) -> 55 | G4: =C4*D4*(E4/100) -> 0 | H4: carte
A5: 45911 | B5: Plateau 20*20 | C5: 1 | D5: 70 | F5: =C5*D5*(1-E5/100) -> 70 | G5: =C5*D5*(E5/100) -> 0 | H5: Espèces
A6: 45911 | B6: Magnet fridge | C6: 1 | D6: 10 | F6: =C6*D6*(1-E6/100) -> 10 | G6: =C6*D6*(E6/100) -> 0 | H6: Espèces
A7: 45911 | B7: Porte clé chachia | C7: 1 | D7: 10 | F7: =C7*D7*(1-E7/100) -> 10 | G7: =C7*D7*(E7/100) -> 0 | H7: Espèces
A8: 45911 | B8: Couffin sac à main | C8: 1 | D8: 110 | E8: =10/110*100 -> 9.0909091 | F8: =C8*D8*(1-E8/100) -> 100 | G8: 10 | H8: Espèces
A9: 45911 | B9: Plateau 20*10 | C9: 1 | D9: 55 | F9: =C9*D9*(1-E9/100) -> 55 | G9: =C9*D9*(E9/100) -> 0 | H9: Espèces
A10: 45911 | B10: Planche Bois | C10: 1 | D10: 35 | F10: =C10*D10*(1-E10/100) -> 35 | G10: =C10*D10*(E10/100) -> 0 | H10: Espèces
A11: 45911 | B11: Fouta | C11: 1 | D11: 25 | E11: 20 | F11: =C11*D11*(1-E11/100) -> 20 | G11: =C11*D11*(E11/100) -> 5 | H11: Espèces
A12: 45912 | B12: Couffin sac à main | C12: 1 | D12: 110 | F12: =C12*D12*(1-E12/100) -> 110 | G12: =C12*D12*(E12/100) -> 0 | H12: carte
A13: 45912 | B13: fridge magnet | C13: 1 | D13: 10 | F13: =C13*D13*(1-E13/100) -> 10 | G13: =C13*D13*(E13/100) -> 0 | H13: carte
A14: 45913 | B14: mouton T3 | C14: 1 | D14: 80 | F14: =C14*D14*(1-E14/100) -> 80 | G14: =C14*D14*(E14/100) -> 0 | H14: carte
A15: 45913 | B15: Planche Bois | C15: 3 | D15: 40 | F15: =C15*D15*(1-E15/100) -> 120 | G15: =C15*D15*(E15/100) -> 0 | H15: carte
A16: 45913 | B16: Sous plat bois | C16: 1 | D16: 40 | F16: =C16*D16*(1-E16/100) -> 40 | G16: =C16*D16*(E16/100) -> 0 | H16: carte
A17: 45913 | B17: Bouteille huile | C17: 2 | D17: 30 | F17: =C17*D17*(1-E17/100) -> 60 | G17: =C17*D17*(E17/100) -> 0 | H17: carte
A18: 45913 | B18: bouteille huile | C18: 1 | D18: 30 | E18: =10/30*100 -> 33.333333 | F18: =C18*D18*(1-E18/100) -> 20 | G18: 10 | H18: Espèces
A19: 45913 | B19: fridge magnet | C19: 1 | D19: 10 | F19: =C19*D19*(1-E19/100) -> 10 | G19: =C19*D19*(E19/100) -> 0 | H19: Espèces
A20: 45913 | B20: bougie sidi bousaid MF | C20: 2 | D20: 50 | F20: =C20*D20*(1-E20/100) -> 100 | G20: =C20*D20*(E20/100) -> 0 | H20: carte
A21: 45913 | B21: bougie trio | C21: 1 | D21: 20 | F21: =C21*D21*(1-E21/100) -> 20 | G21: =C21*D21*(E21/100) -> 0 | H21: carte
A22: 45913 | B22: fridge magnet | C22: 2 | D22: 10 | F22: =C22*D22*(1-E22/100) -> 20 | G22: =C22*D22*(E22/100) -> 0 | H22: carte
A23: 45913 | B23: mouton T3 | C23: 1 | D23: 70 | F23: =C23*D23*(1-E23/100) -> 70 | G23: 0 | H23: Espèces
A24: 45914 | B24: tasse + st coeur irr | C24: 1 | D24: 30 | F24: =C24*D24*(1-E24/100) -> 30 | G24: =C24*D24*(E24/100) -> 0 | H24: Espèces
A25: 45914 | B25: bougie sidi bousaid GF | C25: 1 | D25: 60 | E25: =5/60*100 -> 8.3333333 | F25: =C25*D25*(1-E25/100) -> 55 | G25: =C25*D25*(E25/100) -> 5 | H25: Espèces
A26: 45914 | B26: bouteille huile d'olive poisson pf | C26: 1 | D26: 25 | E26: 20 | F26: =C26*D26*(1-E26/100) -> 20 | G26: =C26*D26*(E26/100) -> 5 | H26: carte
A27: 45914 | B27: Plateau 20*20 | C27: 1 | D27: 70 | F27: =C27*D27*(1-E27/100) -> 70 | G27: =C27*D27*(E27/100) -> 0 | H27: Espèces
A28: 45914 | B28: Bouteille huile d'olive pf | C28: 1 | D28: 25 | F28: =C28*D28*(1-E28/100) -> 25 | G28: =C28*D28*(E28/100) -> 0 | H28: Espèces
A29: 45914 | B29: Tote Bag | C29: 1 | D29: 20 | E29: 25 | F29: =C29*D29*(1-E29/100) -> 15 | G29: =C29*D29*(E29/100) -> 5 | H29: Espèces
A30: 45914 | B30: Magnet fridge | C30: 2 | D30: 10 | F30: =C30*D30*(1-E30/100) -> 20 | G30: =C30*D30*(E30/100) -> 0 | H30: Espèces
A31: 45914 | B31: Fouta | C31: 1 | D31: 20 | F31: =C31*D31*(1-E31/100) -> 20 | G31: =C31*D31*(E31/100) -> 0 | H31: carte
A32: 45914 | B32: Porte clé porte | C32: 2 | D32: 10 | F32: =C32*D32*(1-E32/100) -> 20 | G32: =C32*D32*(E32/100) -> 0 | H32: carte
A33: 45914 | B33: Plateau 30*20 | C33: 1 | D33: 100 | F33: =C33*D33*(1-E33/100) -> 100 | G33: =C33*D33*(E33/100) -> 0 | H33: carte
A34: 45914 | B34: vase Poissons | C34: 1 | D34: 25 | F34: =C34*D34*(1-E34/100) -> 25 | G34: =C34*D34*(E34/100) -> 0 | H34: carte
A35: 45914 | B35: Plateau 30*10 | C35: 1 | D35: 70 | F35: =C35*D35*(1-E35/100) -> 70 | G35: =C35*D35*(E35/100) -> 0 | H35: carte
A36: 45914 | B36: BROC verre GM | C36: 1 | D36: 55 | E36: =5/55*100 -> 9.0909091 | F36: =C36*D36*(1-E36/100) -> 50 | G36: =C36*D36*(E36/100) -> 5 | H36: Espèces
A37: 45915 | B37: Mouton PF | C37: 1 | D37: 50 | F37: =C37*D37*(1-E37/100) -> 50 | G37: =C37*D37*(E37/100) -> 0 | H37: carte
A38: 45915 | B38: Poisson avec Tige | C38: 1 | D38: 90 | F38: =C38*D38*(1-E38/100) -> 90 | G38: =C38*D38*(E38/100) -> 0 | H38: carte
A39: 45915 | B39: Mouton PF | C39: 1 | D39: 50 | F39: =C39*D39*(1-E39/100) -> 50 | G39: =C39*D39*(E39/100) -> 0 | H39: Espèces
A40: 45915 | B40: Porte clé chachia | C40: 1 | D40: 10 | F40: =C40*D40*(1-E40/100) -> 10 | G40: =C40*D40*(E40/100) -> 0 | H40: Espèces
A41: 45916 | B41: Mouton PF | C41: 1 | D41: 50 | E41: 20 | F41: =C41*D41*(1-E41/100) -> 40 | G41: =C41*D41*(E41/100) -> 10 | H41: Espèces
A42: 45917 | B42: Carafe didon Bleue | C42: 1 | D42: 55 | F42: =C42*D42*(1-E42/100) -> 55 | G42: =C42*D42*(E42/100) -> 0 | H42: carte | J42: Cliente anglaise 225 , bougie offerte
A43: 45917 | B43: Carafe Medina Bleue | C43: 1 | D43: 60 | F43: =C43*D43*(1-E43/100) -> 60 | G43: =C43*D43*(E43/100) -> 0 | H43: carte
A44: 45917 | B44: Verre Bleu PF | C44: 2 | D44: 20 | F44: =C44*D44*(1-E44/100) -> 40 | G44: =C44*D44*(E44/100) -> 0 | H44: carte
A45: 45917 | B45: Plateau 30*10 | C45: 1 | D45: 70 | F45: =C45*D45*(1-E45/100) -> 70 | G45: =C45*D45*(E45/100) -> 0 | H45: carte
A46: 45918 | B46: Carafe Didon Miel | C46: 1 | D46: 55 | E46: =5/55*100 -> 9.0909091 | F46: =C46*D46*(1-E46/100) -> 50 | G46: =C46*D46*(E46/100) -> 5 | H46: Espèces | J46: Client algérien commande 308 , tote bag offert
A47: 45918 | B47: Verre Miel PF | C47: 4 | D47: 18 | F47: =C47*D47*(1-E47/100) -> 72 | G47: =C47*D47*(E47/100) -> 0 | H47: Espèces
A48: 45918 | B48: Verre Miel MF | C48: 2 | D48: 18 | F48: =C48*D48*(1-E48/100) -> 36 | G48: =C48*D48*(E48/100) -> 0 | H48: Espèces
A49: 45918 | B49: Bonbonniére Miel | C49: 1 | D49: 50 | F49: =C49*D49*(1-E49/100) -> 50 | G49: =C49*D49*(E49/100) -> 0 | H49: Espèces
A50: 45918 | B50: Bonbonniére ebene | C50: 1 | D50: 50 | F50: =C50*D50*(1-E50/100) -> 50 | G50: =C50*D50*(E50/100) -> 0 | H50: Espèces
A51: 45918 | B51: Bonbonniére trans | C51: 1 | D51: 50 | F51: =C51*D51*(1-E51/100) -> 50 | G51: =C51*D51*(E51/100) -> 0 | H51: Espèces
A52: 45918 | B52: Tasse + st fleur bleue irr | C52: 1 | D52: 30 | F52: =C52*D52*(1-E52/100) -> 30 | G52: =C52*D52*(E52/100) -> 0 | H52: Espèces
A53: 45918 | B53: Porte clé chachia | C53: 3 | D53: 10 | E53: 50 | F53: =C53*D53*(1-E53/100) -> 15 | G53: =C53*D53*(E53/100) -> 15 | H53: Espèces
A54: 45918 | B54: Couffin sac à main | C54: 1 | D54: 110 | E54: =20/110*100 -> 18.181818 | F54: =C54*D54*(1-E54/100) -> 90 | G54: =C54*D54*(E54/100) -> 20 | H54: Espèces
A55: 45918 | B55: Plateau 20*20 | C55: 1 | D55: 70 | F55: =C55*D55*(1-E55/100) -> 70 | G55: =C55*D55*(E55/100) -> 0 | H55: Espèces
A56: 45918 | B56: Couffin sac à main | C56: 1 | D56: 110 | F56: =C56*D56*(1-E56/100) -> 110 | G56: =C56*D56*(E56/100) -> 0 | H56: Espèces | J56: tote bag cadeau
A57: 45918 | B57: Carafe Tanit miel | C57: 1 | D57: 55 | E57: =10/55*100 -> 18.181818 | F57: =C57*D57*(1-E57/100) -> 45 | G57: =C57*D57*(E57/100) -> 10 | H57: Espèces
A58: 45918 | B58: Verre Miel GF | C58: 6 | D58: 20 | E58: 16.666667 | F58: =C58*D58*(1-E58/100) -> 100 | G58: =C58*D58*(E58/100) -> 20 | H58: Espèces
A59: 45918 | B59: Bouteille Huile d'olive fleurs GF | C59: 1 | D59: 30 | E59: =10/30*100 -> 33.333333 | F59: =C59*D59*(1-E59/100) -> 20 | G59: =C59*D59*(E59/100) -> 10 | H59: Espèces
A60: 45918 | B60: Mug emeraude Sougui | C60: 1 | D60: 25 | E60: 20 | F60: =C60*D60*(1-E60/100) -> 20 | G60: =C60*D60*(E60/100) -> 5 | H60: Espèces
A61: 45918 | B61: Plat zouba emeraude | C61: 1 | D61: 40 | E61: 12.5 | F61: =C61*D61*(1-E61/100) -> 35 | G61: =C61*D61*(E61/100) -> 5 | H61: carte
A62: 45918 | B62: Bougie Sidi bousaid MF | C62: 1 | D62: 50 | F62: =C62*D62*(1-E62/100) -> 50 | G62: =C62*D62*(E62/100) -> 0 | H62: Espèces
A63: 45918 | B63: Bonbonniére Miel | C63: 1 | D63: 50 | F63: =C63*D63*(1-E63/100) -> 50 | G63: =C63*D63*(E63/100) -> 0 | H63: Espèces
A64: 45918 | B64: Vase Corps PF | C64: 1 | D64: 20 | F64: =C64*D64*(1-E64/100) -> 20 | G64: =C64*D64*(E64/100) -> 0 | H64: Espèces
A65: 45918 | B65: Verre Miel GF | C65: 12 | D65: 20 | E65: 20 | F65: =C65*D65*(1-E65/100) -> 192 | G65: =C65*D65*(E65/100) -> 48 | H65: Espèces
A66: 45918 | B66: Carafe Medina Miel | C66: 2 | D66: 60 | E66: 10 | F66: =C66*D66*(1-E66/100) -> 108 | G66: =C66*D66*(E66/100) -> 12 | H66: Espèces
A67: 45918 | B67: Bonbonniére trans | C67: 1 | D67: 50 | E67: 20 | F67: =C67*D67*(1-E67/100) -> 40 | G67: =C67*D67*(E67/100) -> 10 | H67: Espèces
A68: 45918 | B68: Verre Bleu GF | C68: 6 | D68: 20 | E68: =20/120*100 -> 16.666667 | F68: =C68*D68*(1-E68/100) -> 100 | G68: =C68*D68*(E68/100) -> 20 | H68: Espèces
A69: 45918 | B69: verre Miel GF | C69: 6 | D69: 20 | E69: =20/120*100 -> 16.666667 | F69: =C69*D69*(1-E69/100) -> 100 | G69: =C69*D69*(E69/100) -> 20 | H69: Espèces
A70: 45919 | B70: Couffin sac à main | C70: 1 | D70: 110 | E70: =30/110*100 -> 27.272727 | F70: =C70*D70*(1-E70/100) -> 80 | G70: =C70*D70*(E70/100) -> 30 | H70: Espèces | J70: Safé Guettat Rotaract , prix spécial
A71: 45919 | B71: Mouton MF | C71: 1 | D71: 60 | F71: =C71*D71*(1-E71/100) -> 60 | G71: =C71*D71*(E71/100) -> 0 | H71: Espèces
A72: 45919 | B72: tasse + st irr | C72: 3 | D72: 30 | F72: =C72*D72*(1-E72/100) -> 90 | G72: =C72*D72*(E72/100) -> 0 | H72: Espèces | J72: Magnet offert
A73: 45919 | B73: Mouton GF | C73: 2 | D73: 80 | E73: =10/160*100 -> 6.25 | F73: =C73*D73*(1-E73/100) -> 150 | G73: =C73*D73*(E73/100) -> 10 | H73: Espèces | J73: Magnet offert
A74: 45920 | B74: Bouteille Huile d'olive PF | C74: 2 | D74: 25 | F74: =C74*D74*(1-E74/100) -> 50 | G74: =C74*D74*(E74/100) -> 0 | H74: Espèces
A75: 45920 | B75: Mug Zouba Vert et mauve | C75: 1 | D75: 30 | F75: =C75*D75*(1-E75/100) -> 30 | G75: =C75*D75*(E75/100) -> 0 | H75: Espèces
A76: 45920 | B76: sous tasse bleu et blanc PF zouba | C76: 1 | D76: 10 | F76: =C76*D76*(1-E76/100) -> 10 | G76: =C76*D76*(E76/100) -> 0 | H76: Espèces
A77: 45920 | B77: Tasse irr sans St | C77: 1 | D77: 20 | E77: 0 | F77: =C77*D77*(1-E77/100) -> 20 | G77: =C77*D77*(E77/100) -> 0 | H77: Espèces
A78: 45920 | B78: Magnet fridge | C78: 2 | D78: 10 | E78: 50 | F78: =C78*D78*(1-E78/100) -> 10 | G78: =C78*D78*(E78/100) -> 10 | H78: Espèces
A79: 45920 | B79: Plateau 20*20 | C79: 1 | D79: 70 | E79: 0 | F79: =C79*D79*(1-E79/100) -> 70 | G79: =C79*D79*(E79/100) -> 0 | H79: Espèces
A80: 45920 | B80: Magnet fridge | C80: 7 | D80: 10 | E80: =10/70*100 -> 14.285714 | F80: =C80*D80*(1-E80/100) -> 60 | G80: =C80*D80*(E80/100) -> 10 | H80: Espèces
A81: 45921 | B81: Verre Miel MF | C81: 4 | D81: 20 | F81: =C81*D81*(1-E81/100) -> 80 | G81: =C81*D81*(E81/100) -> 0 | H81: carte
A82: 45921 | B82: Magnet fridge | C82: 1 | D82: 10 | E82: 50 | F82: =C82*D82*(1-E82/100) -> 5 | G82: =C82*D82*(E82/100) -> 5 | H82: carte
A83: 45921 | B83: Poisson avec Tige | C83: 1 | D83: 90 | F83: =C83*D83*(1-E83/100) -> 90 | G83: =C83*D83*(E83/100) -> 0 | H83: carte
A84: 45922 | B84: Bouteille Huile d'olive PF | C84: 2 | D84: 25 | F84: =C84*D84*(1-E84/100) -> 50 | G84: =C84*D84*(E84/100) -> 0 | H84: Espèces
A85: 45922 | B85: 2 bol zouba + 2creux + plat dessert emraude | C85: 1 | D85: 165 | F85: =C85*D85*(1-E85/100) -> 165 | G85: =C85*D85*(E85/100) -> 0 | H85: carte
A86: 45923 | B86: Tasse + st jasmin PF | C86: 2 | D86: 25 | F86: =C86*D86*(1-E86/100) -> 50 | G86: =C86*D86*(E86/100) -> 0 | H86: Espèces
A87: 45924 | B87: plateau 6 + 2 bobonniére + diffiseur + bouteille pm | C87: 1 | D87: 200 | F87: =C87*D87*(1-E87/100) -> 200 | G87: =C87*D87*(E87/100) -> 0 | H87: Espèces
A88: 45924 | B88: palteau 4 | C88: 2 | D88: 70 | F88: =C88*D88*(1-E88/100) -> 140 | G88: =C88*D88*(E88/100) -> 0 | H88: carte
A89: 45924 | B89: plateau 6 + plateau 2 + porte sous tasses | C89: 1 | D89: 200 | F89: =C89*D89*(1-E89/100) -> 200 | G89: =C89*D89*(E89/100) -> 0 | H89: Espèces
A90: 45924 | B90: mot du coueur solo | C90: 1 | D90: 25 | F90: =C90*D90*(1-E90/100) -> 25 | G90: =C90*D90*(E90/100) -> 0 | H90: Espèces
A91: 45924 | B91: Mouton T2 | C91: 1 | D91: 50 | F91: =C91*D91*(1-E91/100) -> 50 | G91: =C91*D91*(E91/100) -> 0 | H91: Espèces
A92: 45924 | B92: Tote Bag | C92: 1 | D92: 20 | E92: 25 | F92: =C92*D92*(1-E92/100) -> 15 | G92: =C92*D92*(E92/100) -> 5 | H92: Espèces | J92: client m'a donné 5 euros
A93: 45924 | B93: mouton T2 | C93: 2 | D93: 50 | F93: =C93*D93*(1-E93/100) -> 100 | G93: =C93*D93*(E93/100) -> 0 | H93: carte
A94: 45925 | B94: carafe Bled champagne | C94: 1 | D94: 60 | F94: =C94*D94*(1-E94/100) -> 60 | G94: =C94*D94*(E94/100) -> 0 | H94: Espèces
A95: 45925 | B95: Packaging carafe | C95: 1 | D95: 20 | F95: =C95*D95*(1-E95/100) -> 20 | G95: =C95*D95*(E95/100) -> 0 | H95: Espèces
A96: 45925 | B96: tasse ceram bouquet sans St | C96: 1 | D96: 20 | F96: =C96*D96*(1-E96/100) -> 20 | G96: =C96*D96*(E96/100) -> 0 | H96: Espèces
A97: 45925 | B97: tasse irr fleur bleu | C97: 1 | D97: 30 | F97: =C97*D97*(1-E97/100) -> 30 | G97: =C97*D97*(E97/100) -> 0 | H97: Espèces
A98: 45925 | B98: photophote T1 + solo | C98: 1 | D98: 40 | F98: =C98*D98*(1-E98/100) -> 40 | G98: =C98*D98*(E98/100) -> 0 | H98: carte
A99: 45925 | B99: fridge magnet | C99: 1 | D99: 10 | F99: =C99*D99*(1-E99/100) -> 10 | G99: =C99*D99*(E99/100) -> 0 | H99: Espèces
A100: 45926 | B100: photophote T1 | C100: 1 | D100: 20 | F100: =C100*D100*(1-E100/100) -> 20 | G100: =C100*D100*(E100/100) -> 0 | H100: Espèces
...
